{
	"id": "AHefyAvdSaWYQ3L",
	"json": "{\"id\":\"AHefyAvdSaWYQ3L\",\"url\":\"https://avirwebtest.pages.dev/galleries/home-cinema/\",\"loadedUrl\":\"https://avirwebtest.pages.dev/galleries/home-cinema/\",\"uniqueKey\":\"deployed-/galleries/home-cinema/\",\"method\":\"GET\",\"noRetry\":false,\"retryCount\":0,\"errorMessages\":[],\"headers\":{},\"userData\":{\"label\":\"deployed\",\"__crawlee\":{\"state\":4}},\"handledAt\":\"2026-01-30T21:23:41.575Z\"}",
	"method": "GET",
	"orderNo": null,
	"retryCount": 0,
	"uniqueKey": "deployed-/galleries/home-cinema/",
	"url": "https://avirwebtest.pages.dev/galleries/home-cinema/"
}