{
	"id": "dpqrC3RJSuWLgGq",
	"json": "{\"id\":\"dpqrC3RJSuWLgGq\",\"url\":\"https://www.avir.com/post/trinnov-unveils-altitudeci/\",\"loadedUrl\":\"https://www.avir.com/post/trinnov-unveils-altitudeci\",\"uniqueKey\":\"live-/post/trinnov-unveils-altitudeci/\",\"method\":\"GET\",\"noRetry\":false,\"retryCount\":0,\"errorMessages\":[],\"headers\":{},\"userData\":{\"label\":\"live\",\"__crawlee\":{\"state\":4}},\"handledAt\":\"2026-01-31T00:47:25.947Z\"}",
	"method": "GET",
	"orderNo": null,
	"retryCount": 0,
	"uniqueKey": "live-/post/trinnov-unveils-altitudeci/",
	"url": "https://www.avir.com/post/trinnov-unveils-altitudeci/"
}